screenshare/__init__.py
screenshare/__main__.py
screenshare/_version.py
screenshare-23.2.20.dist-info/METADATA
screenshare-23.2.20.dist-info/WHEEL
screenshare-23.2.20.dist-info/entry_points.txt
screenshare-23.2.20.dist-info/top_level.txt
screenshare-23.2.20.dist-info/RECORD
