Metadata-Version: 2.1
Name: screenshare
Version: 23.2.20
Summary: Simple Screensharing
Project-URL: Source, https://github.com/matthias95/screenshare
Requires-Python: >=3.6, <4
Requires-Dist: pynput
Requires-Dist: opencv-python
Requires-Dist: numpy
Requires-Dist: mss
